mxrain-0.1.3.dist-info/DESCRIPTION.rst
mxrain-0.1.3.dist-info/METADATA
mxrain-0.1.3.dist-info/RECORD
mxrain-0.1.3.dist-info/WHEEL
mxrain-0.1.3.dist-info/entry_points.txt
mxrain-0.1.3.dist-info/metadata.json
mxrain-0.1.3.dist-info/top_level.txt
mxrain-0.1.3.dist-info/zip-safe
mxrainsrc/__init__.py
mxrainsrc/mxrain.py
