Metadata-Version: 2.0
Name: mxrain
Version: 0.1.3
Summary: 一个小的测试项目
Home-page: UNKNOWN
Author: rain.xia
Author-email: xjjrain2015@126.com
License: MIT
Keywords: python cli mx rain
Platform: UNKNOWN
